tethys_data_models/__init__.py
tethys_data_models/base.py
tethys_data_models/dataset.py
tethys_data_models/geometry.py
tethys_data_models/permit.py
tethys_data_models/utils.py
tethys_data_models/tests/__init__.py
tethys_data_models-0.4.11.dist-info/LICENSE
tethys_data_models-0.4.11.dist-info/METADATA
tethys_data_models-0.4.11.dist-info/WHEEL
tethys_data_models-0.4.11.dist-info/top_level.txt
tethys_data_models-0.4.11.dist-info/RECORD
