Metadata-Version: 2.1
Name: tethys-data-models
Version: 0.4.11
Summary: Various data models used in data validation for Tethys
Home-page: https://github.com/tethys-ts/tethys-data-models
Author: Mike Kittridge
Author-email: mullenkamp1@gmail.com
License: Apache
Keywords: tethys
Classifier: Development Status :: 3 - Alpha
Classifier: Intended Audience :: Developers
Classifier: Topic :: Scientific/Engineering :: Hydrology
Classifier: License :: OSI Approved :: Apache Software License
Classifier: Programming Language :: Python :: 3.6
Classifier: Programming Language :: Python :: 3.7
Classifier: Programming Language :: Python :: 3.8
Classifier: Programming Language :: Python :: 3.9
License-File: LICENSE
Requires-Dist: pydantic
Requires-Dist: orjson
